dnschef/__init__.py
dnschef/__main__.py
dnschef/api.py
dnschef/kitchen.py
dnschef/logger.py
dnschef/protocols.py
dnschef/utils.py
dnschef_ng-0.7.2.dist-info/LICENSE
dnschef_ng-0.7.2.dist-info/METADATA
dnschef_ng-0.7.2.dist-info/WHEEL
dnschef_ng-0.7.2.dist-info/entry_points.txt
dnschef_ng-0.7.2.dist-info/RECORD
