Metadata-Version: 2.1
Name: dnschef-ng
Version: 0.7.2
Summary: A highly configurable DNS proxy for Penetration Testers and Malware Analysts
License: BSD-3-Clause
Author: iphelix
Author-email: iphelix@thesprawl.org
Requires-Python: >=3.11,<4.0
Classifier: Environment :: Console
Classifier: License :: OSI Approved :: BSD License
Classifier: Programming Language :: Python :: 3
Classifier: Programming Language :: Python :: 3.11
Classifier: Programming Language :: Python :: 3.12
Classifier: Topic :: Security
Provides-Extra: api
Requires-Dist: dnslib (>=0.9.23,<0.10.0)
Requires-Dist: fastapi (>=0.103.1,<0.104.0) ; extra == "api"
Requires-Dist: pydantic-settings (>=2.0.3,<3.0.0) ; extra == "api"
Requires-Dist: rich (>=13.5.3,<14.0.0)
Requires-Dist: structlog (>=23.1.0,<24.0.0)
Requires-Dist: uvicorn (>=0.23.2,<0.24.0) ; extra == "api"
